{
    "项目信息":{
               "报告时间":"time",
               "合同编号":"NA",
               "项目描述":"单细胞转录组测序分析项目",
               "样本物种":"Human",
               "样本类型":"NA",
               "样本数目":"NA"
               },
     "客户信息":{
               "客户姓名":"NA",
               "客户邮箱":"NA"
               },
     "测序信息":{
               "测序类型":"Ilummina X10, paired end (150 cycles + 150 cycles)",
               "数据总量":"NA"
               },
     "分析结果":{
               "测序数据barcode和UMI质量统计信息表":"./01_QC/prefix_QCsummary.xls",
               "单细胞count对数值的密度分布图":"./02_whitelist/prefix_cell_barcode_count_density.png",
               "单细胞count值降序排列对数值分布图":"./02_whitelist/prefix_cell_barcode_counts.png",
               "单细胞count值降序排列累计曲线图":"./02_whitelist/prefix_cell_barcode_knee.png",
               "有效单细胞reads数目分布表":"./03_extract/prefix_cellReadsCounts.tsv",
               "有效单细胞数据统计信息表":"./03_extract/prefix_cellReadsInfo.tsv",
               "基因组比对分析表":"./04_mapAndAssign/prefix_mapstat.tsv",
               "单细胞的nGenenUMI分布图":"./05_scSeqAnalysis/prefix_QCPlot.png",
               "单细胞中nUMI/nGene相关关系展示图":"./05_scSeqAnalysis/prefix_GenePlot.png",
               "细胞过滤情况表":"./05_scSeqAnalysis/prefix_cellFiltered.tsv",
               "下游高质量细胞过滤后统计结果表":"./05_scSeqAnalysis/prefix_saturation.tsv",
               "细胞亚群聚类图":"./05_scSeqAnalysis/prefix_TSNEPlot.png",
               "不同cluster的markerGene展示表":"./05_scSeqAnalysis/prefix_top10_markerGene.csv",
               "各cluster的top10markerGene表达热图":"./05_scSeqAnalysis/prefix_ClusterHeatmap.png"
               }
}









